classconfig/__init__.py
classconfig/base.py
classconfig/classes.py
classconfig/configurable.py
classconfig/transforms.py
classconfig/validators.py
classconfig/yaml.py
classconfig-1.0.17.dist-info/licenses/LICENSE
classconfig-1.0.17.dist-info/METADATA
classconfig-1.0.17.dist-info/WHEEL
classconfig-1.0.17.dist-info/top_level.txt
classconfig-1.0.17.dist-info/RECORD
