Metadata-Version: 2.4
Name: classconfig
Version: 1.0.17
Summary: Package for creating configuration files automatically and loading objects from those configuration files.
Home-page: https://github.com/mdocekal/classconfig
Author: Martin Dočekal
Keywords: configuration,auto config,config,configurable,configurable class,configurable object,configurable attribute
Requires-Python: >=3.9
License-File: LICENSE
Requires-Dist: ruamel.yaml~=0.17.16
Dynamic: author
Dynamic: description
Dynamic: description-content-type
Dynamic: home-page
Dynamic: keywords
Dynamic: license-file
Dynamic: requires-dist
Dynamic: requires-python
Dynamic: summary
